ringcentral/__init__.py
ringcentral/sdk.py
ringcentral/sdk_test.py
ringcentral/core/__init__.py
ringcentral/http/__init__.py
ringcentral/http/api_exception.py
ringcentral/http/api_exception_test.py
ringcentral/http/api_response.py
ringcentral/http/api_response_test.py
ringcentral/http/client.py
ringcentral/http/client_test.py
ringcentral/http/json_object.py
ringcentral/http/multipart_builder.py
ringcentral/http/multipart_builder_test.py
ringcentral/platform/__init__.py
ringcentral/platform/auth.py
ringcentral/platform/events.py
ringcentral/platform/platform.py
ringcentral/platform/platform_test.py
ringcentral/test/__init__.py
ringcentral/test/spy.py
ringcentral/test/testcase.py
ringcentral/websocket/__init__.py
ringcentral/websocket/events.py
ringcentral/websocket/web_socket_client.py
ringcentral/websocket/web_socket_subscription.py
ringcentral-0.9.0.dist-info/LICENSE.md
ringcentral-0.9.0.dist-info/METADATA
ringcentral-0.9.0.dist-info/WHEEL
ringcentral-0.9.0.dist-info/top_level.txt
ringcentral-0.9.0.dist-info/RECORD
